MANIFEST.in
README
REQUIREMENTS
distribute_setup.py
setup.py
src/django_cssmin.egg-info/PKG-INFO
src/django_cssmin.egg-info/SOURCES.txt
src/django_cssmin.egg-info/dependency_links.txt
src/django_cssmin.egg-info/requires.txt
src/django_cssmin.egg-info/top_level.txt
src/djcssmin/__init__.py
src/djcssmin/commands.py
src/djcssmin/utils.py