Metadata-Version: 1.0
Name: django-cssmin
Version: 0.3
Summary: CSS compression for Django.
Home-page: http://bitbucket.org/zacharyvoase/django-cssmin
Author: Zachary Voase
Author-email: zacharyvoase@me.com
License: UNKNOWN
Platform: UNKNOWN
